flask_sl.py
setup.py
Flask_SL.egg-info/PKG-INFO
Flask_SL.egg-info/SOURCES.txt
Flask_SL.egg-info/dependency_links.txt
Flask_SL.egg-info/not-zip-safe
Flask_SL.egg-info/requires.txt
Flask_SL.egg-info/top_level.txt