Metadata-Version: 1.1
Name: Flask-SL
Version: 0.0.3
Summary: Basic recognition of Second Life® requests.
Home-page: https://github.com/nivardus/flask-sl
Author: Bennett Goble
Author-email: nivardus@gmail.com
License: MIT
Download-URL: https://github.com/nivardus/flask-sl/archive/v0.0.3.tar.gz
Platform: any
Classifier: Development Status :: 2 - Pre-Alpha
Classifier: Environment :: Web Environment
Classifier: Intended Audience :: Developers
Classifier: License :: OSI Approved :: BSD License
Classifier: Operating System :: OS Independent
Classifier: Programming Language :: Python
Classifier: Topic :: Internet :: WWW/HTTP :: Dynamic Content
Classifier: Topic :: Software Development :: Libraries :: Python Modules
Classifier: Topic :: Games/Entertainment :: Simulation
